e3/py.typed
e3/aws/__init__.py
e3/aws/cfn/__init__.py
e3/aws/cfn/codecommit.py
e3/aws/cfn/iam.py
e3/aws/cfn/ini.py
e3/aws/cfn/main.py
e3/aws/cfn/route53.py
e3/aws/cfn/s3.py
e3/aws/cfn/service_discovery.py
e3/aws/cfn/arch/__init__.py
e3/aws/cfn/arch/security.py
e3/aws/cfn/ec2/__init__.py
e3/aws/cfn/ec2/security.py
e3/aws/dynamodb/__init__.py
e3/aws/ec2/__init__.py
e3/aws/ec2/ami.py
e3/aws/handler/__init__.py
e3/aws/handler/s3.py
e3/aws/pricing/__init__.py
e3/aws/s3/__init__.py
e3/aws/troposphere/__init__.py
e3/aws/troposphere/apigateway/__init__.py
e3/aws/troposphere/awslambda/__init__.py
e3/aws/troposphere/awslambda/flask.py
e3/aws/troposphere/awslambda/flask_apigateway_wrapper.py
e3/aws/troposphere/cloudformation/__init__.py
e3/aws/troposphere/cloudfront/__init__.py
e3/aws/troposphere/cloudfront/data/__init__.py
e3/aws/troposphere/cloudfront/data/lambda_invalidate_head.py
e3/aws/troposphere/cloudwatch/__init__.py
e3/aws/troposphere/config/__init__.py
e3/aws/troposphere/config/config_rule.py
e3/aws/troposphere/config/configuration_recorder.py
e3/aws/troposphere/dynamodb/__init__.py
e3/aws/troposphere/ec2/__init__.py
e3/aws/troposphere/ecr/__init__.py
e3/aws/troposphere/ecr/repository.py
e3/aws/troposphere/ecs/__init__.py
e3/aws/troposphere/ecs/cluster.py
e3/aws/troposphere/ecs/task_definition.py
e3/aws/troposphere/ecs/vpc.py
e3/aws/troposphere/events/__init__.py
e3/aws/troposphere/events/rule.py
e3/aws/troposphere/iam/__init__.py
e3/aws/troposphere/iam/managed_policy.py
e3/aws/troposphere/iam/policy_document.py
e3/aws/troposphere/iam/policy_statement.py
e3/aws/troposphere/iam/role.py
e3/aws/troposphere/s3/__init__.py
e3/aws/troposphere/s3/bucket.py
e3/aws/troposphere/secretsmanager/__init__.py
e3/aws/troposphere/sns/__init__.py
e3/aws/troposphere/sqs/__init__.py
e3/aws/util/__init__.py
e3/aws/util/ecr.py
e3_aws-22.5.0.dist-info/licenses/LICENSE
e3_aws-22.5.0.dist-info/METADATA
e3_aws-22.5.0.dist-info/WHEEL
e3_aws-22.5.0.dist-info/entry_points.txt
e3_aws-22.5.0.dist-info/top_level.txt
e3_aws-22.5.0.dist-info/RECORD
