Metadata-Version: 2.4
Name: e3-aws
Version: 22.5.0
Summary: E3 Cloud Formation Extensions
Author: AdaCore's IT Team
License-File: LICENSE
Requires-Dist: boto3
Requires-Dist: botocore
Requires-Dist: docker; platform_system == "Linux"
Requires-Dist: e3-core
Requires-Dist: pyyaml
Requires-Dist: troposphere
Provides-Extra: test
Requires-Dist: awscli; extra == "test"
Requires-Dist: pytest; extra == "test"
Requires-Dist: pytest-html; extra == "test"
Requires-Dist: mock; extra == "test"
Requires-Dist: requests_mock; extra == "test"
Requires-Dist: httpretty; extra == "test"
Requires-Dist: flask; extra == "test"
Requires-Dist: moto[dynamodb,sts]; extra == "test"
Provides-Extra: check
Requires-Dist: mypy==1.8.0; extra == "check"
Requires-Dist: pytest; extra == "check"
Requires-Dist: flask; extra == "check"
Requires-Dist: moto[dynamodb,sts]; extra == "check"
Requires-Dist: bandit; extra == "check"
Requires-Dist: pip-audit; extra == "check"
Requires-Dist: types-colorama; extra == "check"
Requires-Dist: types-psutil; extra == "check"
Requires-Dist: types-python-dateutil; extra == "check"
Requires-Dist: types-PyYAML; extra == "check"
Requires-Dist: types-requests; extra == "check"
Requires-Dist: types-setuptools; extra == "check"
Dynamic: license-file
